{
  "restorans": {
"McDonalds":[{"id":"1", "name": "Біг тейсті", "img":"https://brfood.com.ua/files/products/hero.sdwch_bigtasty.300x300.png", "price":"112"},
               {"id":"2","name": "Біг маг", "img":"https://brfood.com.ua/files/products/hero.sdwch_bigmac.300x300.png", "price":"72"},
               {"id":"3","name": "Біг Техас", "img":"https://brfood.com.ua/files/products/aitccbifm8iqzhidd36v.1000x1000.300x300.png", "price":"114"},
               {"id":"4","name": "Чізбургер", "img":"https://brfood.com.ua/files/products/hero.sdwch_cheeseburger-1.300x300.png", "price":"36"},
               {"id":"5","name": "МакЧікен", "img":"https://brfood.com.ua/files/products/hero.sdwch_mcchicken.300x300.png", "price":"64"},
               {"id":"6","name": "Гамбургер", "img":"https://brfood.com.ua/files/products/hero.sdwch_hamburger.300x300.png", "price":"31"},
               {"id":"7","name": "Філе-о-фіш", "img":"https://brfood.com.ua/files/products/hero.sdwch_file-o-fish.300x300.png", "price":"64"}
              ],
    "KFC":[{"id":"8","name": "Чізургер", "img":"https://www.kfc-ukraine.com/admin/files/medium/medium_4061.jpg", "price":"50"},
               {"id":"9","name": "Лонгер", "img":"https://www.kfc-ukraine.com/admin/files/medium/medium_3737.jpg", "price":"36"},
               {"id":"10","name": "Тост 2 сиру", "img":"https://www.kfc-ukraine.com/admin/files/medium/medium_4065.jpg", "price":"25"},
               {"id":"11","name": "Дабл Чікен", "img":"https://brfood.com.ua/files/products/hero.sdwch_cheeseburger-1.300x300.png", "price":"100"},
               {"id":"12","name": "Чікенбургер гострий", "img":"https://www.kfc-ukraine.com/admin/files/medium/medium_4063.jpg", "price":"75"},
               {"id":"13","name": "Чікенбургер", "img":"https://www.kfc-ukraine.com/admin/files/medium/medium_4064.jpg", "price":"75"},
               {"id":"14","name": "Тост український", "img":"https://www.kfc-ukraine.com/admin/files/medium/medium_4068.jpg", "price":"40"}
              ],
    "Ris":[{"id":"15","name": "Динаміт", "img":"https://ris.od.ua/wp-content/uploads/dar_5509-500x500.jpg", "price":"195"},
               {"id":"16","name": "Канні хот", "img":"https://ris.od.ua/wp-content/uploads/dar_5511-500x500.jpg", "price":"190"},
               {"id":"17","name": "Нагасакі", "img":"https://ris.od.ua/wp-content/uploads/dar_5504-500x500.jpg", "price":"218"},
               {"id":"18","name": "Чикаго", "img":"https://ris.od.ua/wp-content/uploads/dar_5508-500x500.jpg", "price":"278"},
               {"id":"19","name": "Акай", "img":"https://ris.od.ua/wp-content/uploads/akaj_1-500x500.jpg", "price":"250"},
               {"id":"20","name": "Банзай", "img":"https://ris.od.ua/wp-content/uploads/banzaj_1-500x500.jpg", "price":"240"},
               {"id":"21","name": "Кодзима", "img":"https://ris.od.ua/wp-content/uploads/kodzima_1-500x500.jpg", "price":"245"},
           {"id":"22","name": "Фусіто", "img":"https://ris.od.ua/wp-content/uploads/fusito-roll-500x500.jpg", "price":"190"}
              ]
  }
   
}
